varela/__init__.py
varela/algorithm.py
varela/app.py
varela/applogger.py
varela/batch.py
varela/parser.py
varela/test.py
varela/utils.py
varela-0.3.1.dist-info/licenses/LICENSE
varela-0.3.1.dist-info/METADATA
varela-0.3.1.dist-info/WHEEL
varela-0.3.1.dist-info/entry_points.txt
varela-0.3.1.dist-info/top_level.txt
varela-0.3.1.dist-info/RECORD
