Metadata-Version: 2.4
Name: varela
Version: 0.3.1
Summary: Compute the Approximate Vertex Cover for undirected graph encoded in DIMACS format.
Home-page: https://github.com/frankvegadelgado/varela
Author: Frank Vega
Author-email: vega.frank@gmail.com
License: MIT License
Project-URL: Source Code, https://github.com/frankvegadelgado/varela
Project-URL: Documentation Research, https://dev.to/frank_vega_987689489099bf/efficient-vertex-cover-approximation-via-iterative-dominating-set-transformations-40i9
Classifier: Topic :: Scientific/Engineering
Classifier: Topic :: Software Development
Classifier: Development Status :: 5 - Production/Stable
Classifier: License :: OSI Approved :: MIT License
Classifier: Programming Language :: Python :: 3.10
Classifier: Environment :: Console
Classifier: Intended Audience :: Developers
Classifier: Intended Audience :: Education
Classifier: Intended Audience :: Information Technology
Classifier: Intended Audience :: Science/Research
Classifier: Natural Language :: English
Requires-Python: >=3.10
License-File: LICENSE
Requires-Dist: baldor>=0.1.4
Dynamic: author
Dynamic: author-email
Dynamic: classifier
Dynamic: description
Dynamic: description-content-type
Dynamic: home-page
Dynamic: license
Dynamic: license-file
Dynamic: project-url
Dynamic: requires-dist
Dynamic: requires-python
Dynamic: summary
